Workbook

Sheet Summary
A1: Job list — 162 open roles (researched Oct 28, 2026)
A2: How to use: go to "All Roles". Use the filter arrows in the header row to filter by Category, Location, Type or Fit.
A3: Red rows are due within 7 days; yellow within 3 weeks; struck-through gray = deadline passed.
A4: Set "My status" (dropdown) as you apply; applied rows turn green.
A5: Found via web search: open each link to confirm the posting is live before applying. Eligibility notes are in the Notes column.
A7: Category | B7: Roles | C7: Fit 4-5 | E7: Deadline window | F7: Roles | H7: My progress | I7: Count
A8: AI / research | B8: =COUNTIF('All Roles'!$F$2:$F$163,A8) -> 5 | C8: =COUNTIFS('All Roles'!$F$2:$F$163,A8,'All Roles'!$J$2:$J$163,">=4") -> 2 | E8: Due in 7 days | F8: =COUNTIFS('All Roles'!$B$2:$B$163,">=0",'All Roles'!$B$2:$B$163,"<=7") -> 15 | H8: To apply | I8: =COUNTIF('All Roles'!$N$2:$N$163,H8) -> 162
A9: Biotech/pharma – BD / alliance / PM | B9: =COUNTIF('All Roles'!$F$2:$F$163,A9) -> 2 | C9: =COUNTIFS('All Roles'!$F$2:$F$163,A9,'All Roles'!$J$2:$J$163,">=4") -> 1 | E9: Due in 8-30 days | F9: =COUNTIFS('All Roles'!$B$2:$B$163,">=8",'All Roles'!$B$2:$B$163,"<=30") -> 15 | H9: Applied | I9: =COUNTIF('All Roles'!$N$2:$N$163,H9) -> 0
A10: Biotech/pharma – R&D / lab | B10: =COUNTIF('All Roles'!$F$2:$F$163,A10) -> 1 | C10: =COUNTIFS('All Roles'!$F$2:$F$163,A10,'All Roles'!$J$2:$J$163,">=4") -> 1 | E10: Due later | F10: =COUNTIF('All Roles'!$B$2:$B$163,">30") -> 13 | H10: Interview R1 | I10: =COUNTIF('All Roles'!$N$2:$N$163,H10) -> 0
A11: Biotech/pharma – regulatory | B11: =COUNTIF('All Roles'!$F$2:$F$163,A11) -> 8 | C11: =COUNTIFS('All Roles'!$F$2:$F$163,A11,'All Roles'!$J$2:$J$163,">=4") -> 4 | E11: Rolling / no deadline | F11: =COUNTIF('All Roles'!$A$2:$A$163,"Rolling") -> 119 | H11: Offer | I11: =COUNTIF('All Roles'!$N$2:$N$163,H11) -> 0
A12: Biotech/pharma – strategy / commercial | B12: =COUNTIF('All Roles'!$F$2:$F$163,A12) -> 16 | C12: =COUNTIFS('All Roles'!$F$2:$F$163,A12,'All Roles'!$J$2:$J$163,">=4") -> 7 | E12: Deadline passed | F12: =COUNTIF('All Roles'!$B$2:$B$163,"<0") -> 0 | H12: Skip | I12: =COUNTIF('All Roles'!$N$2:$N$163,H12) -> 0
A13: Clinical research / data | B13: =COUNTIF('All Roles'!$F$2:$F$163,A13) -> 24 | C13: =COUNTIFS('All Roles'!$F$2:$F$163,A13,'All Roles'!$J$2:$J$163,">=4") -> 5
A14: Healthcare / life sciences consulting | B14: =COUNTIF('All Roles'!$F$2:$F$163,A14) -> 18 | C14: =COUNTIFS('All Roles'!$F$2:$F$163,A14,'All Roles'!$J$2:$J$163,">=4") -> 5
A15: Hedge fund / equity research | B15: =COUNTIF('All Roles'!$F$2:$F$163,A15) -> 12 | C15: =COUNTIFS('All Roles'!$F$2:$F$163,A15,'All Roles'!$J$2:$J$163,">=4") -> 4
A16: Investment banking | B16: =COUNTIF('All Roles'!$F$2:$F$163,A16) -> 7 | C16: =COUNTIFS('All Roles'!$F$2:$F$163,A16,'All Roles'!$J$2:$J$163,">=4") -> 2
A17: Investor relations | B17: =COUNTIF('All Roles'!$F$2:$F$163,A17) -> 3 | C17: =COUNTIFS('All Roles'!$F$2:$F$163,A17,'All Roles'!$J$2:$J$163,">=4") -> 0
A18: Management consulting | B18: =COUNTIF('All Roles'!$F$2:$F$163,A18) -> 4 | C18: =COUNTIFS('All Roles'!$F$2:$F$163,A18,'All Roles'!$J$2:$J$163,">=4") -> 0
A19: Marketing / content / media | B19: =COUNTIF('All Roles'!$F$2:$F$163,A19) -> 14 | C19: =COUNTIFS('All Roles'!$F$2:$F$163,A19,'All Roles'!$J$2:$J$163,">=4") -> 5
A20: Other | B20: =COUNTIF('All Roles'!$F$2:$F$163,A20) -> 14 | C20: =COUNTIFS('All Roles'!$F$2:$F$163,A20,'All Roles'!$J$2:$J$163,">=4") -> 4
A21: Product / tech | B21: =COUNTIF('All Roles'!$F$2:$F$163,A21) -> 16 | C21: =COUNTIFS('All Roles'!$F$2:$F$163,A21,'All Roles'!$J$2:$J$163,">=4") -> 3
A22: Venture capital / private markets | B22: =COUNTIF('All Roles'!$F$2:$F$163,A22) -> 18 | C22: =COUNTIFS('All Roles'!$F$2:$F$163,A22,'All Roles'!$J$2:$J$163,">=4") -> 6
A23: Total | B23: =SUM(B8:B22) -> 162 | C23: =SUM(C8:C22) -> 49

Sheet All Roles
A1: Deadline | B1: Days left | C1: Company | D1: Role (click to open) | E1: Type | F1: Category | G1: Location | H1: Remote? | I1: Pay (as listed) | J1: Fit (1-5) | K1: Resume to use | L1: Why it fits you | M1: Notes / eligibility | N1: My status | O1: Date applied
A2: 46323 | B2: =IF(ISNUMBER(A2),A2-TODAY(),"") -> 0 | C2: Analysis Group | D2: Associate - Health Care (HEOR, Epidemiology & Market Access) (2027 Start Date) | E2: Full-time | F2: Healthcare / life sciences consulting | G2: Boston, MA | H2: Unknown | I2: Not listed | J2: 4 | K2: Consulting (BlueMatter) | L2: HEOR/market-access work uses her clinical-research data, R/Python and biotech MS; Associate is AG's master's-level entry. | M2: Posted 8 Oct 2026. A third-party guide lists the Health Care deadline as 28 Oct 2026 (today) with rolling review after. Associate level usually targets master's/PhD grads; check her MS qualifies. Pay not shown. Link is an aggregator, so apply via analysisgroup.com careers. | N2: To apply
A3: 46323 | B3: =IF(ISNUMBER(A3),A3-TODAY(),"") -> 0 | C3: Piper Sandler | D3: Campus Recruiting - 2027 Investment Banking Analyst - Healthcare | E3: Full-time | F3: Investment banking | G3: New York, NY | H3: On-site | I3: $110,000 | J3: 5 | K3: Finance (Jefferies) | L3: NYC healthcare IB analyst seat for the class of 2027, a top-tier target in her top city. | M3: An aggregator shows it open until 10/28/2026 (today), posted about a week ago, so apply immediately or confirm on Piper's Workday. Class of 2027, no sponsorship. | N3: To apply
A4: 46325 | B4: =IF(ISNUMBER(A4),A4-TODAY(),"") -> 2 | C4: ClearView Healthcare Partners | D4: Life Sciences Strategy Analyst (September 2027 Start Date) | E4: Full-time | F4: Healthcare / life sciences consulting | G4: Unknown (GMT deadline suggests London office) | H4: Unknown | I4: Not listed | J4: 4 | K4: Consulting (BlueMatter) | L4: Life-sciences strategy analyst cohort built for life-sci grads; her Pfizer GRS and rare-disease work map directly. | M4: Eligibility: Life Sciences degree graduating Dec 2026–Aug 2027 (she fits). Cohort starts 13 Sep 2027; applications close 30 Oct 2026 11:59pm GMT; interviews from late Nov, rolling. Deadline from Greenhouse posting text in search results. Office not confirmed (likely London, which is Tier 2). The $92.5k pay seen online is for the US summer-start cohort (closed 15 Jul), so I left pay blank. | N4: To apply
A5: 46325 | B5: =IF(ISNUMBER(A5),A5-TODAY(),"") -> 2 | C5: ClearView Healthcare Partners | D5: Life Sciences Summer Analyst Intern (Summer 2027) - London | E5: Internship | F5: Healthcare / life sciences consulting | G5: London, UK | H5: On-site | I5: £37k annualised (employer-provided, per Glassdoor UK) | J5: 3 | K5: Consulting (BlueMatter) | L5: London life sciences strategy internship (12 Jul-10 Sep 2027) built on forecasting and research work she has already done at Pfizer. | M5: STRETCH: wants grads from Dec 2027 to Aug 2028, and she graduates May 2027, so she's likely ineligible. Apply for the full-time London Analyst role instead. Deadline 30 Oct 2026, 11:59pm GMT, per the Glassdoor UK listing (not used as the link). Pay is in GBP. A UK internship needs a GAE-type visa. The link is the Greenhouse board root. | N5: To apply
A6: 46325 | B6: =IF(ISNUMBER(A6),A6-TODAY(),"") -> 2 | C6: Roivant Sciences | D6: Rotational Analyst Program (Class of 2027) | E6: Full-time | F6: Biotech/pharma – BD / alliance / PM | G6: New York, NY | H6: On-site | I6: $100,000/yr (per aggregators; not confirmed on Roivant's own posting) | J6: 5 | K6: Finance (Jefferies) | L6: Two-year, four-rotation program across Roivant and its Vants that suits her mix of biotech science, VC database, financial modeling and rare-disease work, in NYC. | M6: Starts July 2027. Requires a 4-year US undergrad graduating Dec 2026–Jun 2027, GPA 3.5+, relocation to NYC; she meets all three. The Oct 30 expiry comes from the Harvard career-services copy. A Dartmouth copy of Greenhouse ID 8099164 showed an expiry of Sep 11, 2026, so the live requisition ID may differ. Check Roivant's Greenhouse board and apply today. | N6: To apply
A7: 46325 | B7: =IF(ISNUMBER(A7),A7-TODAY(),"") -> 2 | C7: Merck & Co. | D7: 2027 Future Talent Program – Regulatory Chemistry, Manufacturing and Controls (CMC) Intern | E7: Internship | F7: Biotech/pharma – regulatory | G7: Rahway, NJ | H7: Unknown | I7: Not listed | J7: 4 | K7: General | L7: Regulatory submissions for biologics and small molecules suit her biotech MS and wet-lab background, in the NYC metro. | M7: An aggregator (bebee) lists it as open until 10/30/2026, so it is urgent. Returning-student requirement applies. Verify on jobs.merck.com. | N7: To apply
A8: 46325 | B8: =IF(ISNUMBER(A8),A8-TODAY(),"") -> 2 | C8: Roblox | D8: [2027] Associate Product Manager, Early Career | E8: Full-time | F8: Product / tech | G8: San Mateo, CA | H8: Hybrid | I8: $143,000 | J8: 4 | K8: Product (Anthropic) | L8: 21-month rotational APM in the Bay Area that explicitly accepts business degrees; her PM internship and AI-agent build make her a credible applicant. | M8: One listing says applications close Fri Oct 30 at 5pm PST (rolling review); Simplify shows 10/31/26. Apply by Oct 30 to be safe. Hybrid, 3 days on-site; no H1B sponsorship. Link is an aggregator; the official Roblox careers page didn't appear in results. Fairly sure it's open (2 days left). Soft gap: gaming/consumer domain. | N8: To apply
A9: 46325 | B9: =IF(ISNUMBER(A9),A9-TODAY(),"") -> 2 | C9: Blackstone | D9: 2027 Blackstone Tactical Opportunities Summer Analyst (London) | E9: Internship | F9: Venture capital / private markets | G9: London, UK | H9: On-site | I9: Not listed | J9: 3 | K9: Finance (Jefferies) | L9: Top-brand PE seat in London (tier 2); flexible-capital deals include healthcare. | M9: Deadline 'Friday 30 October' per the listing; a guide also says the UK window ran Jun 15–Oct 30, 2026. Apply now. UK right-to-work and penultimate-year eligibility risks. | N9: To apply
A10: 46325 | B10: =IF(ISNUMBER(A10),A10-TODAY(),"") -> 2 | C10: Blackstone | D10: 2027 Blackstone Private Wealth Summer Analyst (London) | E10: Internship | F10: Investor relations | G10: London, UK | H10: On-site | I10: Not listed | J10: 3 | K10: Finance (Jefferies) | L10: Investor-facing alternatives distribution role at Blackstone, close to IR. | M10: Deadline taken from a guide saying the UK programme closes Oct 30, 2026; the role's own page wasn't seen. Work-authorization and eligibility risks. Moderate confidence. | N10: To apply
A11: 46326 | B11: =IF(ISNUMBER(A11),A11-TODAY(),"") -> 3 | C11: JPMorganChase | D11: 2027 Marketing Leadership Development Program - Full-Time Analyst | E11: Full-time | F11: Marketing / content / media | G11: New York, NY (also Columbus, OH) | H11: On-site | I11: Not listed | J11: 5 | K11: General | L11: 2-year rotational marketing program in NYC; 85k-follower creator with paid brand deals plus analytics is exactly the MLDP profile | M11: Full-time track wants grads Dec 2026-Jun 2027, which she meets; 3.2 GPA min; no H1B. Deadline 10/31/26 from Opportunities for Youth and Simplify (Prosple marks a copy expired), so apply immediately. The $80k figure in results is for the summer-analyst version (grads Dec 2027-Jun 2028), so full-time pay is left blank. JPM is on the big-name list. | N11: To apply
A12: 46326 | B12: =IF(ISNUMBER(A12),A12-TODAY(),"") -> 3 | C12: Merck | D12: 2027 Future Talent Program - Epidemiology and RWE Capabilities & Analytics - Intern | E12: Internship | F12: Clinical research / data | G12: Upper Gwynedd, PA / Rahway, NJ / West Point, PA / Boston, MA | H12: Unknown | I12: $39,908 - $111,111 (annualized range) | J12: 4 | K12: General | L12: Real-world health data analytics at a big-name pharma, matching her Jefferson clinical data and R/SQL work. | M12: URGENT: the posting end date is 10/31/26 (from a Simplify listing). It is for grad students in epi/biostat/public health/data science, so her MS-stage status needs to qualify. Merck FTP interns are generally expected to be enrolled. Search jobs.merck.com for the official requisition. | N12: To apply
A13: 46326 | B13: =IF(ISNUMBER(A13),A13-TODAY(),"") -> 3 | C13: Mount Sinai Health System | D13: Clinical Research Coordinator I (Dr. Kontorovich's Lab) - Cardiovascular Research Institute | E13: Full-time | F13: Clinical research / data | G13: New York, NY | H13: On-site | I13: Not listed | J13: 3 | K13: General | L13: Entry CRC role at an NYC academic medical center that builds on her Jefferson clinical research data analyst role. | M13: Posted 2026-09-26, valid through 2026-10-31 (listing data). It is an immediate-start hire, not a 2027 start, so there is a timing mismatch. Mount Sinai CRC I pay runs about $58k-74k, below the bar. The link is a ZipRecruiter mirror; find it on careers.mountsinai.org. | N13: To apply
... A44: 46418 | B44: =IF(ISNUMBER(A44),A44-TODAY(),"") -> 95 | C44: Kleiner Perkins | D44: 2027 Kleiner Perkins Engineering Fellow | E44: Internship | F44: Product / tech | G44: San Francisco Bay Area | H44: On-site | I44: Not listed | J44: 3 | K44: Product (Anthropic) | L44: Summer at a KP portfolio startup plus a founder network; her AI-agent building and Python make a stretch case. | M44: Deadline Jan 31, 2027, 11:59pm PST, per the Ashby listing, with rolling review. A stretch because the track is for software engineers. The Design track's Harvard listing shows a Nov 3, 2026 expiry, which conflicts. Summer-after-graduation eligibility not confirmed. No Product Fellow track found for 2027. | N44: To apply
A45: Rolling | B45: =IF(ISNUMBER(A45),A45-TODAY(),"") | C45: Mercor | D45: Strategic Project Associate | E45: Full-time | F45: AI / research | G45: San Francisco, CA (or NYC/London) | H45: On-site | I45: $120k base + equity | J45: 5 | K45: Product (Anthropic) | L45: Runs $10M+ data projects for AI labs; her paid work with OpenAI/Google/Anthropic/AWS plus her AI-agent build fits directly | M45: Glassdoor copy targets Dec '26 or May/Jun '27 grads (some older copies say '25/'26). Simplify updated it 10/8/26, so it looks actively recruited. Five days a week in office. Fairly confident it's open. | N45: To apply
A46: Rolling | B46: =IF(ISNUMBER(A46),A46-TODAY(),"") | C46: IQVIA | D46: Associate Consultant, Market Access Strategy Consulting (July 2027 start) | E46: Full-time | F46: Healthcare / life sciences consulting | G46: San Francisco, CA / Boston, MA | H46: On-site | I46: $65,400 - $163,600 (aggregator-listed) | J46: 5 | K46: Consulting (BlueMatter) | L46: Big-data pharma market-access analytics in SF, a direct fit for her SQL/Python, Pfizer cost modeling and rare-disease work. | M46: The 'Start Date: July 2027' field came from a job-board mirror of the same requisition; IQVIA's own page lists it as office-based in Boston/SF. Pay band is from aggregators, not verified. No deadline found. Fairly confident it is open. | N46: To apply
A47: Rolling | B47: =IF(ISNUMBER(A47),A47-TODAY(),"") | C47: Guidehouse | D47: Consultant - Life Sciences Advisory, Health Segment - Campus 2027 | E47: Full-time | F47: Healthcare / life sciences consulting | G47: New York, NY | H47: Hybrid | I47: $81,000-$135,000 + discretionary bonus | J47: 5 | K47: Consulting (BlueMatter) | L47: Campus-hire consultant level aimed at master's grads finishing by summer 2027; her BS/MS fits the level above analyst. | M47: For grad students with a master's expected by summer 2027 (her MS is May 2027). F-1/J-1 excluded. Link is an aggregator; find the same title on guidehouse.wd1.myworkdayjobs.com. No deadline found. Campus 2027 postings looked active (sister Analyst req posted about 21 days ago). Midpoint pay meets the bar. | N47: To apply
A48: Rolling | B48: =IF(ISNUMBER(A48),A48-TODAY(),"") | C48: Piper Sandler | D48: 2027 Investment Banking Analyst - Healthcare Biotech | E48: Full-time | F48: Investment banking | G48: San Francisco, CA | H48: On-site | I48: $110,000 | J48: 5 | K48: Finance (Jefferies) | L48: Class-of-2027 biotech IB analyst in Tier-1 SF; her DCF/3-statement skills and biotech VC database are directly relevant. | M48: Asks for May/June 2027 grads (she fits). Starts June 2027 with Minneapolis training. No sponsorship. No deadline found; a sister Piper req expires 23 Dec 2026. Link is an aggregator; search the title on pipersandler.wd501.myworkdayjobs.com. | N48: To apply
A49: Rolling | B49: =IF(ISNUMBER(A49),A49-TODAY(),"") | C49: Pfizer | D49: Global Regulatory Sciences Rotational Program (cohort starting Summer 2027) | E49: Full-time | F49: Biotech/pharma – regulatory | G49: Unknown (Pfizer GRS; she interned with GRS in NYC) | H49: Unknown | I49: Not listed | J49: 5 | K49: General | L49: A two-year regulatory rotational program in the same Global Regulatory Sciences organization where she built an AI agent for regulatory QA in summer 2026. | M49: Pfizer's early-careers page says the next cohort begins Summer 2027, but I found no application dates or eligibility details. Deadline is unknown, so it is marked Rolling. Medium confidence that it is open. She should also ask her 2026 GRS manager or recruiter directly. | N49: To apply
A50: Rolling | B50: =IF(ISNUMBER(A50),A50-TODAY(),"") | C50: Merck & Co. | D50: 2027 Future Talent Program – Global Regulatory Affairs & Compliance US Subsidiary Intern (Drug Shortages & Support Functions) | E50: Internship | F50: Biotech/pharma – regulatory | G50: Rahway, NJ | H50: Unknown | I50: Not listed | J50: 5 | K50: General | L50: Regulatory intelligence and strategy work in the NYC metro, a direct continuation of her Pfizer regulatory internship. | M50: Posted Sep 8, 2026 (aggregator); no close date seen, and Merck postings stay up until a candidate pool is identified, so apply soon. Merck's program requires returning to school after the internship; her BS/MS may or may not count. Other 2027 Merck postings show about $39k–111k annualized, unconfirmed for this role, so pay is left blank. Verify on jobs.merck.com. | N50: To apply
A51: Rolling | B51: =IF(ISNUMBER(A51),A51-TODAY(),"") | C51: Solace (Solace Health) | D51: Influencer Marketing Associate (College Grad 2027) | E51: Full-time | F51: Marketing / content / media | G51: Redwood City, CA | H51: On-site | I51: Not listed | J51: 5 | K51: General | L51: Health-tech creator marketing role for 2027 grads; her 85k-follower science channel and paid brand deals are exactly the creator-side expertise they want. | M51: Posted ~Aug 25, 2026 (Menlo VC board and netinfluencer); no deadline seen, so it may fill on a rolling basis. Pay not listed (may be under $100k; startup, Series C). Healthcare angle means handling patient stories and disclosures. Link is Menlo Ventures' job board, not Solace's own ATS. Moderately sure it's still open. | N51: To apply
A52: Rolling | B52: =IF(ISNUMBER(A52),A52-TODAY(),"") | C52: Candid Health | D52: Customer Strategy & Ops - New Grad (2027) | E52: Full-time | F52: Other | G52: San Francisco, CA / New York, NY / Denver, CO | H52: Hybrid | I52: $90,000-$110,000 + equity | J52: 4 | K52: General | L52: Health-tech strategy & ops role that owns customer outcomes; it uses her clinical-data and healthcare background and her founder ownership | M52: Explicitly for fall 2026/spring 2027 grads. Base is a little under the $100k bar (Indeed shows up to $120k). Hybrid is 4 days in office, with up to 25% travel. Posted late Aug 2026; no deadline seen. | N52: To apply
A53: Rolling | B53: =IF(ISNUMBER(A53),A53-TODAY(),"") | C53: Google | D53: Customer Growth Associate, Google Customer Solutions, University Graduate, 2027 Start | E53: Full-time | F53: Marketing / content / media | G53: New York, NY / San Francisco, CA | H53: On-site | I53: $72k-$102k + 30% bonus target + equity | J53: 4 | K53: General | L53: Google ads growth/consulting role for new grads in NYC or SF; her brand-deal and analytics experience fits client growth work | M53: Google is on the big-name list, so the base below the bar is fine. Status is uncertain: posted 8/14/26, and one copy is marked no longer accepting while Handshake shows validThrough 2027-07-20. Prefers a July 2027 start. Check before applying. | N53: To apply
A54: Rolling | B54: =IF(ISNUMBER(A54),A54-TODAY(),"") | C54: Uber | D54: New York - Strategic Finance Intern - 2027 | E54: Internship | F54: Other | G54: New York, NY | H54: Unknown | I54: $32.80/hr | J54: 4 | K54: Finance (Jefferies) | L54: Finance & Strategy internship in NYC that uses her DCF/3-statement modeling and Pfizer cost-modeling work | M54: Posted 9/14/26 on the University team. Graduation-window eligibility wasn't visible; Uber's 2027 intern roles often require Dec 2027+ grads, so there's a return-to-school risk (her BS/MS may help). An SF version also appears on aggregators. | N54: To apply
A55: Rolling | B55: =IF(ISNUMBER(A55),A55-TODAY(),"") | C55: Whatnot | D55: Category Associate - New Grad Business Program | E55: Full-time | F55: Marketing / content / media | G55: New York, NY / San Francisco, CA / Los Angeles, CA | H55: On-site | I55: $81,000-$90,000 | J55: 4 | K55: General | L55: Live-shopping new-grad rotation spanning seller onboarding, influencer partnerships, marketing and analytics; built for a creator-founder | M55: Requires graduating by summer 2027, which she meets. Pay is under the $100k bar. On-site in a hub. No deadline seen; listed on Ashby and Whatnot careers. | N55: To apply
A56: Rolling | B56: =IF(ISNUMBER(A56),A56-TODAY(),"") | C56: TikTok | D56: Creative Product Operations Graduate (International Advertising - Creative and Brand Innovation) - 2027 Start | E56: Full-time | F56: Marketing / content / media | G56: San Jose, CA | H56: On-site | I56: $76K-$128K | J56: 4 | K56: General | L56: Global Spark rotational program for the class of 2027 on creator marketing and GenAI ad tools, a direct match for her creator and AI-brand work | M56: One copy lists a Master's in Business or related as the minimum. Her BS/MS is biotech, so that's a soft gap. Asks for SQL/Python/BI, which she has. Rolling review; no NYC version found. | N56: To apply
... A163: Rolling | B163: =IF(ISNUMBER(A163),A163-TODAY(),"") | C163: Apollo Global Management | D163: 2027 Summer Analyst (Class of 2028 postings) | E163: Internship | F163: Venture capital / private markets | G163: New York, NY | H163: On-site | I163: $90,000–$100,000 annualized (third-party guide) | J163: 3 | K163: Finance (Jefferies) | L163: Top-brand alternatives firm with summer analyst postings still live in early October. | M163: Weak lead: only a third-party guide says two Class of 2028 summer analyst postings were live as of Oct 2, 2026. No ATS link seen, and the NYC location is assumed from Apollo's HQ. Class of 2028 eligibility risk. Low confidence; check apollo.com/careers. | N163: To apply
